hmmpy/base.py
hmmpy/mle.py
hmmpy/__init__.py
hmmpy/hmm_cython.cpython-38-x86_64-linux-gnu.so
hmmpy/sampler.py
hmmpy/hmm_t_em.py
hmmpy/hmm_online.py
hmmpy/jump.py
hmmpy/finance/merge_data.py
hmmpy/finance/backtest_alternatives.py
hmmpy/finance/backtest.py
hmmpy/finance/__init__.py
hmmpy/finance/mpc_model.py
hmmpy/utils/data_prep.py
hmmpy/utils/simulate_returns.py
hmmpy/utils/__init__.py
hmmpy/utils/plotting/plot_hmm.py
hmmpy/utils/plotting/__init__.py
hmm_py-0.0.2.dist-info/RECORD
hmm_py-0.0.2.dist-info/WHEEL
hmm_py-0.0.2.dist-info/METADATA
hmm_py-0.0.2.dist-info/LICENSE
hmm_py-0.0.2.dist-info/top_level.txt
