Metadata-Version: 2.1
Name: hmm-py
Version: 0.0.2
Summary: A python module to implement Hidden Markov hidden_markov for financial times series.
Home-page: https://github.com/Cstolborg/hmmpy
Author: Cstolborg
Author-email: christianstolborg@gmail.com
License: UNKNOWN
Platform: UNKNOWN
Classifier: Programming Language :: Cython
Classifier: Programming Language :: Python
Classifier: Programming Language :: Python :: 3
Classifier: License :: OSI Approved :: MIT License
Classifier: Operating System :: OS Independent
Requires-Python: >=3.8
Requires-Dist: numpy (>=1.20.1)
Requires-Dist: scikit-learn (>=0.24.0)
Requires-Dist: scipy (>=1.5.4)
Requires-Dist: pandas (>=1.2.0)
Requires-Dist: tqdm
Requires-Dist: cython
Provides-Extra: docs
Requires-Dist: Sphinx ; extra == 'docs'
Requires-Dist: sphinx-gallery ; extra == 'docs'
